<?xml version="1.0" encoding="UTF-8" standalone="no"?>
<empleados>
	<empleado id="002">
		<nombre>miguel</nombre>
		<dept>infor</dept>
		<sueldo>3000.0</sueldo>
		<fechaNacimiento>1966-07-01</fechaNacimiento>
	</empleado>
	<empleado id ="003">
		<nombre>pedro</nombre>
		<dept>lengua</dept>
		<sueldo>2000.0</sueldo>
		<fechaNacimiento>1968-12-01</fechaNacimiento>
	</empleado>
	<empleado id ="007">
		<nombre>james</nombre>
		<dept>secreto</dept>
		<sueldo>8000.0</sueldo>
		<fechaNacimiento>2000-07-01</fechaNacimiento>
	</empleado>
</empleados>